git_switch/__init__.py
git_switch/cli.py
git_switch/pat_manager.py
git_switch/ssh_manager.py
git_switch_cli-0.1.3.dist-info/licenses/LICENSE
git_switch_cli-0.1.3.dist-info/METADATA
git_switch_cli-0.1.3.dist-info/WHEEL
git_switch_cli-0.1.3.dist-info/entry_points.txt
git_switch_cli-0.1.3.dist-info/top_level.txt
git_switch_cli-0.1.3.dist-info/RECORD
