Metadata-Version: 2.4
Name: git-switch-cli
Version: 0.1.3
Summary: Effortlessly manage multiple Git identities and SSH keys. Generate keys, save per-profile Git name/email, and switch profiles in one command. Auto-updates ~/.ssh include and your global Git config for GitHub/GitLab.
Author: Shrinivas Prabhu
License: MIT License
Classifier: License :: OSI Approved :: MIT License
Classifier: Programming Language :: Python :: 3
Classifier: Programming Language :: Python :: 3 :: Only
Classifier: Programming Language :: Python :: 3.9
Classifier: Programming Language :: Python :: 3.10
Classifier: Programming Language :: Python :: 3.11
Classifier: Programming Language :: Python :: 3.12
Classifier: Programming Language :: Python :: 3.13
Requires-Python: >=3.9
License-File: LICENSE
Dynamic: license-file
